Metadata-Version: 2.3
Name: django-oauth2-codeflow
Version: 1.0.0
Summary: Authenticate with any OpenId Connect/Oauth2 provider through authorization code flow. PKCE is also supported.
License: MIT
Keywords: oauth2,oidc,openid
Author: Melih Sünbül
Author-email: m.sunbul@excellence-cloud.com
Maintainer: Melih Sünbül
Maintainer-email: m.sunbul@excellence-cloud.com
Requires-Python: >=3.8,<4.0
Classifier: Development Status :: 5 - Production/Stable
Classifier: Environment :: Web Environment
Classifier: Framework :: Django
Classifier: Framework :: Django :: 4.2
Classifier: Framework :: Django :: 5.0
Classifier: Framework :: Django :: 5.1
Classifier: Framework :: Django :: 5.2
Classifier: Intended Audience :: Developers
Classifier: License :: OSI Approved :: MIT License
Classifier: Natural Language :: English
Classifier: Operating System :: OS Independent
Classifier: Programming Language :: Python :: 3
Classifier: Programming Language :: Python :: 3.8
Classifier: Programming Language :: Python :: 3.9
Classifier: Programming Language :: Python :: 3.10
Classifier: Programming Language :: Python :: 3.11
Classifier: Programming Language :: Python :: 3.12
Classifier: Programming Language :: Python :: 3.13
Classifier: Topic :: Internet :: WWW/HTTP :: Session
Classifier: Topic :: Security
Classifier: Topic :: Software Development :: Libraries :: Python Modules
Classifier: Typing :: Typed
Requires-Dist: django (>=4.2)
Requires-Dist: python-jose[cryptography] (>=3.3)
Requires-Dist: requests (>=2.28)
Project-URL: Bug Tracker, https://github.com/ExcellenceCloudGmbH/django-oauth2-codeflow/issues
Project-URL: Changelog, https://github.com/ExcellenceCloudGmbH/django-oauth2-codeflow/blob/master/CHANGELOG.md
Project-URL: Contributing, https://github.com/ExcellenceCloudGmbH/django-oauth2-codeflow/blob/master/CONTRIBUTING.md
Project-URL: Documentation, https://github.com/ExcellenceCloudGmbH/django-oauth2-codeflow/blob/master/README.md
Project-URL: Github mirror, https://github.com/ExcellenceCloudGmbH/django-oauth2-codeflow
Project-URL: Repository, https://github.com/ExcellenceCloudGmbH/django-oauth2-codeflow
